docked/__init__.py
docked/_formatters.py
docked/_image.py
docked/_stage.py
docked/_types.py
docked/cmd.py
docked/py.typed
docked/_linter/__init__.py
docked/_linter/_checks.py
docked/_linter/_lint.py
docked/_linter/_violation.py
docked/_linter/_violations.py
docked/_steps/__init__.py
docked/_steps/_base.py
docked/_steps/_build.py
docked/_steps/_run.py
docked-0.1.0.dist-info/entry_points.txt
docked-0.1.0.dist-info/LICENSE
docked-0.1.0.dist-info/WHEEL
docked-0.1.0.dist-info/METADATA
docked-0.1.0.dist-info/RECORD
