Metadata-Version: 2.1
Name: docked
Version: 0.1.0
Summary: A human-friendly alternative to Dockerfile.
Keywords: docker,dockerfile,generator,container,containers,pythonic
Author-email: Gram <git@orsinium.dev>
Requires-Python: >=3.8
Classifier: Development Status :: 5 - Production/Stable
Classifier: Intended Audience :: Developers
Classifier: License :: OSI Approved :: MIT License
Classifier: Programming Language :: Python
Classifier: Typing :: Typed
Requires-Dist: sphinx ; extra == "docs"
Requires-Dist: myst-parser ; extra == "docs"
Requires-Dist: isort ; extra == "lint"
Requires-Dist: flake8 ; extra == "lint"
Requires-Dist: unify ; extra == "lint"
Requires-Dist: mypy ; extra == "lint"
Requires-Dist: pytest ; extra == "test"
Requires-Dist: pytest-cov ; extra == "test"
Project-URL: Source, https://github.com/orsinium-labs/docked
Provides-Extra: docs
Provides-Extra: lint
Provides-Extra: test
